{
    "user":
            [
            {"name":"Siva",
            "location":"Bengaluru",
            "likes":64,
            "description": "Kick start your career",
            "PostImage": "https://images.unsplash.com/photo-1583121274602-3e2820c69888?ixlib=rb-1.2.1&ixid=MnwxMjA3fDB8MHxwaG90by1wYWdlfHx8fGVufDB8fHx8&auto=format&fit=crop&w=870&q=80",
            "date": 5241
            },
            {"name":"Neeraj",
            "location":"Pune",
            "likes":30,
            "description": "Sample Description",
            "PostImage": "https://images.unsplash.com/photo-1553440569-bcc63803a83d?ixlib=rb-1.2.1&ixid=MnwxMjA3fDB8MHxwaG90by1wYWdlfHx8fGVufDB8fHx8&auto=format&fit=crop&w=825&q=80",
            "date": 12345
            },
            {"name":"Rahul",
            "location":"Hyderabad",
            "likes":30,
            "description": "Sample Description for Post",
            "PostImage": "https://images.unsplash.com/photo-1552519507-da3b142c6e3d?ixlib=rb-1.2.1&ixid=MnwxMjA3fDB8MHxwaG90by1wYWdlfHx8fGVufDB8fHx8&auto=format&fit=crop&w=870&q=80",
            "date": 6666
            }
            ]
}
